guild/__init__.py
guild/_api.py
guild/_lex.py
guild/_test.py
guild/_yacc.py
guild/ansi_util.py
guild/batch_main.py
guild/batch_util.py
guild/cli.py
guild/click_util.py
guild/cmd_impl_support.py
guild/cmd_notify.py
guild/config.py
guild/entry_point_util.py
guild/exit_code.py
guild/fail.py
guild/file_util.py
guild/filter.py
guild/filter_util.py
guild/flag_util.py
guild/guildfile.py
guild/help.py
guild/index.py
guild/init.py
guild/ipy.py
guild/lock.py
guild/log.py
guild/main.py
guild/main_bootstrap.py
guild/manifest.py
guild/model.py
guild/model_proxy.py
guild/namespace.py
guild/op.py
guild/op_cmd.py
guild/op_dep.py
guild/op_main.py
guild/op_util.py
guild/opref.py
guild/package.py
guild/package_main.py
guild/pass.py
guild/pip_util.py
guild/plugin.py
guild/publish.py
guild/python_util.py
guild/r_util.py
guild/remote.py
guild/remote_run_support.py
guild/remote_util.py
guild/resolver.py
guild/resource.py
guild/resourcedef.py
guild/run.py
guild/run_check.py
guild/run_id.py
guild/run_manifest.py
guild/run_merge.py
guild/run_util.py
guild/run_zip_proxy.py
guild/service.py
guild/serving_util.py
guild/steps_main.py
guild/steps_util.py
guild/summary.py
guild/tabview.py
guild/tensorboard.py
guild/tensorboard_util.py
guild/tfevent.py
guild/uat.py
guild/util.py
guild/var.py
guild/vcs_util.py
guild/view.py
guild/yaml_util.py
guild/_skopt/__init__.py
guild/_skopt/acquisition.py
guild/_skopt/benchmarks.py
guild/_skopt/callbacks.py
guild/_skopt/plots.py
guild/_skopt/searchcv.py
guild/_skopt/utils.py
guild/_skopt/learning/__init__.py
guild/_skopt/learning/forest.py
guild/_skopt/learning/gbrt.py
guild/_skopt/learning/gaussian_process/__init__.py
guild/_skopt/learning/gaussian_process/gpr.py
guild/_skopt/learning/gaussian_process/kernels.py
guild/_skopt/optimizer/__init__.py
guild/_skopt/optimizer/base.py
guild/_skopt/optimizer/dummy.py
guild/_skopt/optimizer/forest.py
guild/_skopt/optimizer/gbrt.py
guild/_skopt/optimizer/gp.py
guild/_skopt/optimizer/optimizer.py
guild/tests/samples/packages/gpkg.mnist-0.1.0.dist-info/DESCRIPTION.rst
guild/tests/samples/packages/gpkg.mnist-0.1.0.dist-info/INSTALLER
guild/tests/samples/packages/gpkg.mnist-0.1.0.dist-info/METADATA
guild/tests/samples/packages/gpkg.mnist-0.1.0.dist-info/RECORD
guild/tests/samples/packages/gpkg.mnist-0.1.0.dist-info/WHEEL
guild/tests/samples/packages/gpkg.mnist-0.1.0.dist-info/entry_points.txt
guild/tests/samples/packages/gpkg.mnist-0.1.0.dist-info/metadata.json
guild/tests/samples/packages/gpkg.mnist-0.1.0.dist-info/namespace_packages.txt
guild/tests/samples/packages/gpkg.mnist-0.1.0.dist-info/top_level.txt
guildai-0.9.0.dist-info/LICENSE.txt
guildai-0.9.0.dist-info/METADATA
guildai-0.9.0.dist-info/WHEEL
guildai-0.9.0.dist-info/entry_points.txt
guildai-0.9.0.dist-info/top_level.txt
guildai-0.9.0.dist-info/RECORD
